<?xml version="1.0" encoding="utf-8" ?>
<dwsync>
<file name="fonctions_Xslt.php" server="newhttpd.vjf.cnrs.fr//var/www/html/lacito/" local="131226583330000000" remote="131226583330000000" />
<file name="textRsc.xsl" server="newhttpd.vjf.cnrs.fr//var/www/html/lacito/" local="131226606300000000" remote="131227704430000000" />
<file name="listRsc.xsl" server="newhttpd.vjf.cnrs.fr//var/www/html/lacito/" local="131226630430000000" remote="131227699160000000" />
<file name="metadata_lacito_old.xml" server="newhttpd.vjf.cnrs.fr//var/www/html/lacito/" local="131226606290000000" remote="131227704410000000" />
<file name="metadata_lacito.xml" server="newhttpd.vjf.cnrs.fr//var/www/html/lacito/" local="131226606280000000" remote="131227701790000000" />
<file name="listRsc_lieu.xsl" server="newhttpd.vjf.cnrs.fr//var/www/html/lacito/" local="131226606260000000" remote="131227699160000000" />
<file name="showOtherText.xsl" server="newhttpd.vjf.cnrs.fr//var/www/html/lacito/" local="131226606300000000" remote="131227704420000000" />
<file name="showText.xsl" server="newhttpd.vjf.cnrs.fr//var/www/html/lacito/" local="131227416907807257" remote="131227704430000000" />
<file name="listLanguages.xsl" server="newhttpd.vjf.cnrs.fr//var/www/html/lacito/" local="131226606260000000" remote="131227699150000000" />
<file name=".fonctions_Xslt.php.swp" server="newhttpd.vjf.cnrs.fr//var/www/html/lacito/" local="131226606260000000" remote="131227699140000000" />
<file name="corpora_list.xml" server="newhttpd.vjf.cnrs.fr//var/www/html/lacito/" local="131226606260000000" remote="131227699150000000" />
<file name="showText.xsl" server="C:/Program Files/EasyPHP-12.1/www/lacito2/" local="131226606300000000" remote="131226606300000000" />
<file name="fonctions_Xslt.php" server="C:/Program Files/EasyPHP-12.1/www/lacito2/" local="131226583330000000" remote="131226583330000000" />
<file name="listRsc.xsl" server="C:/Program Files/EasyPHP-12.1/www/lacito2/" local="131226630430000000" remote="131226630430000000" />
</dwsync>